[
  {
    "id": "task_1771775859135",
    "timestamp": "2026-02-23T00:57:39.135723",
    "keyword": "아디다스",
    "mode": "keyword",
    "collected_count": 10,
    "kream_count": 0,
    "duration_seconds": 16,
    "data": [
      {
        "이미지URL": "https://cdn.poizon.com/pro-img/origin-img/20251206/dcadf0f628994560983e894ea3aca225.jpg",
        "상품번호": "KK3774",
        "제품명": "아디다스 VL 코트 클래식 미끄럼 방지+내마모성 로우탑 독일군 스니커즈 남녀공용 레드",
        "SPU_ID": "23223876",
        "상태": "입찰 가능",
        "최근30일평균거래가": "₩54,000",
        "중국노출": "₩51,000",
        "중국시장최근30일판매량": 39000,
        "중국시장최근30일판매량_원본": "39,000+",
        "현지판매자최근30일판매량": 5,
        "현지판매자최근30일판매량_원본": "<5"
      },
      {
        "이미지URL": "https://cdn.poizon.com/pro-img/origin-img/20251209/318fe0c373ac44168c4a829b024be271.jpg",
        "상품번호": "JQ4238",
        "제품명": "아디다스 바레다 내마모성 로우탑 독일군 스니커즈 남녀공용 그린 화이트",
        "SPU_ID": "18796935",
        "상태": "입찰 가능",
        "최근30일평균거래가": "₩52,000",
        "중국노출": "₩53,000",
        "중국시장최근30일판매량": 22000,
        "중국시장최근30일판매량_원본": "22,000+",
        "현지판매자최근30일판매량": 5,
        "현지판매자최근30일판매량_원본": "<5"
      },
      {
        "이미지URL": "https://cdn.poizon.com/pro-img/origin-img/20251209/917e82fcc5804057baed313791775130.jpg",
        "상품번호": "JI0496",
        "제품명": "아디다스 Vl 코트 2.0 세미 블루 버스트 코어 화이트",
        "SPU_ID": "9206296",
        "상태": "입찰 가능",
        "최근30일평균거래가": "₩55,000",
        "중국노출": "₩52,000",
        "중국시장최근30일판매량": 39000,
        "중국시장최근30일판매량_원본": "39,000+",
        "현지판매자최근30일판매량": 5,
        "현지판매자최근30일판매량_원본": "<5"
      },
      {
        "이미지URL": "https://cdn.poizon.com/pro-img/origin-img/20260126/fbaa4a8919f44a928d36397f61c318c5.png",
        "상품번호": "JP9959",
        "제품명": "아디다스 엔트랩 스케이트보드화 로우탑 화이트/깊이 실버 메탈/레진 옐로우 남녀공용",
        "SPU_ID": "13763546",
        "상태": "입찰 가능",
        "최근30일평균거래가": "₩57,000",
        "중국노출": "₩56,000",
        "중국시장최근30일판매량": 23000,
        "중국시장최근30일판매량_원본": "23,000+",
        "현지판매자최근30일판매량": 5,
        "현지판매자최근30일판매량_원본": "<5"
      },
      {
        "이미지URL": "https://cdn.poizon.com/pro-img/origin-img/20251205/ff607c66f5224524b2e0d748ff75530b.png",
        "상품번호": "HQ1801",
        "제품명": "아디다스 Vl 코트 2.0 블랙 화이트",
        "SPU_ID": "4962345",
        "상태": "입찰 가능",
        "최근30일평균거래가": "₩57,000",
        "중국노출": "₩49,000",
        "중국시장최근30일판매량": 18000,
        "중국시장최근30일판매량_원본": "18,000+",
        "현지판매자최근30일판매량": 22,
        "현지판매자최근30일판매량_원본": "22"
      },
      {
        "이미지URL": "https://cdn.poizon.com/pro-img/origin-img/20250329/02da699e6c194f588239ba8642f9ed3e.jpg",
        "상품번호": "H46099",
        "제품명": "아디다스 에센셜 웜 업 삼선 트랙 자켓 블랙",
        "SPU_ID": "1719418",
        "상태": "입찰 가능",
        "최근30일평균거래가": "₩57,000",
        "중국노출": "₩53,000",
        "중국시장최근30일판매량": 15000,
        "중국시장최근30일판매량_원본": "15,000+",
        "현지판매자최근30일판매량": 400,
        "현지판매자최근30일판매량_원본": "400+"
      },
      {
        "이미지URL": "https://cdn.poizon.com/pro-img/origin-img/20250401/7aa886bc36884e469bfcb8afdc7728ea.jpg",
        "상품번호": "GV5350",
        "제품명": "아디다스 스포츠웨어 D11 빅 배플 다운 후드 자켓 블랙",
        "SPU_ID": "2093977",
        "상태": "입찰 가능",
        "최근30일평균거래가": "₩109,000",
        "중국노출": "₩88,000",
        "중국시장최근30일판매량": 41000,
        "중국시장최근30일판매량_원본": "41,000+",
        "현지판매자최근30일판매량": 5,
        "현지판매자최근30일판매량_원본": "<5"
      },
      {
        "이미지URL": "https://cdn.poizon.com/pro-img/origin-img/20251206/1aa04f5a1ab140be99ef4f0946eb615d.jpg",
        "상품번호": "JR7077",
        "제품명": "아디다스 그랜드 코트 베이스 00s 합성 가죽, 전사 가공 분할 소가죽 로우탑 스케이트보드 신발 남녀공용 그린 블랙 화이트",
        "SPU_ID": "19123963",
        "상태": "입찰 가능",
        "최근30일평균거래가": "₩54,000",
        "중국노출": "₩53,000",
        "중국시장최근30일판매량": 16000,
        "중국시장최근30일판매량_원본": "16,000+",
        "현지판매자최근30일판매량": 5,
        "현지판매자최근30일판매량_원본": "<5"
      },
      {
        "이미지URL": "https://cdn.poizon.com/pro-img/origin-img/20251207/ae1ab75e68a74472a95c8c07ab22850d.jpg",
        "상품번호": "IH6185",
        "제품명": "아디다스 그랜드 코트 베이스 00s 스웨이드 로우탑 스케이트보드 신발 남녀공용 그레이 화이트",
        "SPU_ID": "13329335",
        "상태": "입찰 가능",
        "최근30일평균거래가": "₩60,000",
        "중국노출": "₩58,000",
        "중국시장최근30일판매량": 25000,
        "중국시장최근30일판매량_원본": "25,000+",
        "현지판매자최근30일판매량": 5,
        "현지판매자최근30일판매량_원본": "<5"
      },
      {
        "이미지URL": "https://cdn.poizon.com/pro-img/origin-img/20251205/3c7a21cafd5b4d01b46bd05f18c43f0b.jpg",
        "상품번호": "JR7110",
        "제품명": "(W) 아디다스 그랜드 코트 베이스 00s 세미 핑크 스파크 클리어 핑크",
        "SPU_ID": "18901936",
        "상태": "입찰 가능",
        "최근30일평균거래가": "₩47,000",
        "중국노출": "₩47,000",
        "중국시장최근30일판매량": 10000,
        "중국시장최근30일판매량_원본": "10,000+",
        "현지판매자최근30일판매량": 5,
        "현지판매자최근30일판매량_원본": "<5"
      }
    ],
    "status": "completed"
  },
  {
    "id": "task_1771774801848",
    "timestamp": "2026-02-23T00:40:01.848176",
    "keyword": "나이키",
    "mode": "keyword",
    "collected_count": 10,
    "kream_count": 0,
    "duration_seconds": 14,
    "data": [
      {
        "이미지URL": "https://cdn.poizon.com/pro-img/origin-img/20251206/e6d8ceec010d43b398a366a6dfe76265.jpg",
        "상품번호": "CW2288-111",
        "제품명": "나이키 에어 포스 1 07 가죽 내마모성 로우탑 스케이트보드 신발 남성 퓨어 화이트",
        "SPU_ID": "1237506",
        "상태": "입찰 가능",
        "최근30일평균거래가": "₩122,000",
        "중국노출": "₩114,000",
        "중국시장최근30일판매량": 40000,
        "중국시장최근30일판매량_원본": "40,000+",
        "현지판매자최근30일판매량": 3400,
        "현지판매자최근30일판매량_원본": "3,400+"
      },
      {
        "이미지URL": "https://cdn.poizon.com/pro-img/origin-img/20251209/82dfe339d5ab4ecda1717de90ba89335.jpg",
        "상품번호": "415445-102",
        "제품명": "나이키 에어 군주 4 화이트 네이비 텍스타일, 가죽 미끄럼방지 로우탑 청키 스니커즈 남성 블루 화이트",
        "SPU_ID": "10903",
        "상태": "입찰 가능",
        "최근30일평균거래가": "₩76,000",
        "중국노출": "₩73,000",
        "중국시장최근30일판매량": 28000,
        "중국시장최근30일판매량_원본": "28,000+",
        "현지판매자최근30일판매량": 300,
        "현지판매자최근30일판매량_원본": "300+"
      },
      {
        "이미지URL": "https://cdn.poizon.com/pro-img/origin-img/20251207/1b520d2f371d4f209aa09f98cf4beabd.jpg",
        "상품번호": "FZ0627-010",
        "제품명": "나이키 에어포스 1 '07 블랙 화이트",
        "SPU_ID": "5633013",
        "상태": "입찰 가능",
        "최근30일평균거래가": "₩107,000",
        "중국노출": "₩101,000",
        "중국시장최근30일판매량": 62000,
        "중국시장최근30일판매량_원본": "62,000+",
        "현지판매자최근30일판매량": 400,
        "현지판매자최근30일판매량_원본": "400+"
      },
      {
        "이미지URL": "https://cdn.poizon.com/pro-img/origin-img/20251206/b109f99c34df43b6ae3b4465000ddd03.jpg",
        "상품번호": "CW2288-001",
        "제품명": "나이키 에어 포스 1 07 M - 블랙 / CW2288-001",
        "SPU_ID": "1237477",
        "상태": "입찰 가능",
        "최근30일평균거래가": "₩107,000",
        "중국노출": "₩99,000",
        "중국시장최근30일판매량": 36000,
        "중국시장최근30일판매량_원본": "36,000+",
        "현지판매자최근30일판매량": 100,
        "현지판매자최근30일판매량_원본": "100+"
      },
      {
        "이미지URL": "https://cdn.poizon.com/pro-img/origin-img/20251205/cce47a111e60409ba6e4c1b4ebf0c1d1.jpg",
        "상품번호": "CJ9179-200",
        "제품명": "나이키 에어포스 1 '07 Wb 플랙스",
        "SPU_ID": "47668",
        "상태": "입찰 가능",
        "최근30일평균거래가": "₩123,000",
        "중국노출": "₩113,000",
        "중국시장최근30일판매량": 36000,
        "중국시장최근30일판매량_원본": "36,000+",
        "현지판매자최근30일판매량": 100,
        "현지판매자최근30일판매량_원본": "100+"
      },
      {
        "이미지URL": "https://cdn.poizon.com/pro-img/origin-img/20251128/82975a8523044841a22e5d384dcddf45.jpg",
        "상품번호": "IQ1119-011",
        "제품명": "나이키 에어 포스 1 통기성 좋은 로우탑 스케이트보드 신발 남성 화이트",
        "SPU_ID": "32334179",
        "상태": "입찰 가능",
        "최근30일평균거래가": "₩158,000",
        "중국노출": "₩146,000",
        "중국시장최근30일판매량": 43000,
        "중국시장최근30일판매량_원본": "43,000+",
        "현지판매자최근30일판매량": 5,
        "현지판매자최근30일판매량_원본": "<5"
      },
      {
        "이미지URL": "https://cdn.poizon.com/pro-img/origin-img/20251225/04595976f3ed4b1194d6cfbc1d7d92e5.jpg",
        "상품번호": "DV5456-104",
        "제품명": "(GS) 나이키 코트 버로우 로우 리크래프트 화이트 블랙",
        "SPU_ID": "5393642",
        "상태": "입찰 가능",
        "최근30일평균거래가": "₩58,000",
        "중국노출": "₩54,000",
        "중국시장최근30일판매량": 41000,
        "중국시장최근30일판매량_원본": "41,000+",
        "현지판매자최근30일판매량": 2600,
        "현지판매자최근30일판매량_원본": "2,600+"
      },
      {
        "이미지URL": "https://cdn.poizon.com/pro-img/origin-img/20251206/002d13339da643c9a095b9a2f32d0fb9.jpg",
        "상품번호": "DD1391-100",
        "제품명": "나이키 덩크 로우 레트로 블랙",
        "SPU_ID": "1237613",
        "상태": "입찰 가능",
        "최근30일평균거래가": "₩99,000",
        "중국노출": "₩74,000",
        "중국시장최근30일판매량": 14000,
        "중국시장최근30일판매량_원본": "14,000+",
        "현지판매자최근30일판매량": 200,
        "현지판매자최근30일판매량_원본": "200+"
      },
      {
        "이미지URL": "https://cdn.poizon.com/pro-img/origin-img/20251225/809fe11c9126495c8bf288532d929158.jpg",
        "상품번호": "DH2920-111",
        "제품명": "나이키 에어 포스 1 레 가죽 미끄럼 방지, 쿠셔닝, 내마모성 로우탑 아동 스케이트보드화 퓨어 화이트 남녀공용",
        "SPU_ID": "1389355",
        "상태": "입찰 가능",
        "최근30일평균거래가": "₩89,000",
        "중국노출": "₩85,000",
        "중국시장최근30일판매량": 12000,
        "중국시장최근30일판매량_원본": "12,000+",
        "현지판매자최근30일판매량": 5,
        "현지판매자최근30일판매량_원본": "<5"
      },
      {
        "이미지URL": "https://cdn.poizon.com/pro-img/origin-img/20251207/219f3b12b39142f599520867d7831e76.jpg",
        "상품번호": "DD8959-100",
        "제품명": "나이키 에어 포스 1 07 W - 화이트 / DD8959-100",
        "SPU_ID": "1190436",
        "상태": "입찰 가능",
        "최근30일평균거래가": "₩111,000",
        "중국노출": "₩103,000",
        "중국시장최근30일판매량": 15000,
        "중국시장최근30일판매량_원본": "15,000+",
        "현지판매자최근30일판매량": 500,
        "현지판매자최근30일판매량_원본": "500+"
      }
    ],
    "status": "completed"
  }
]